dmon/__init__.py
dmon/__main__.py
dmon/cli.py
dmon/config.py
dmon/constants.py
dmon/control.py
dmon/py.typed
dmon/runner.py
dmon/types.py
dmon/utils.py
python_dmon-0.3.0.dist-info/WHEEL
python_dmon-0.3.0.dist-info/entry_points.txt
python_dmon-0.3.0.dist-info/METADATA
python_dmon-0.3.0.dist-info/RECORD
