Metadata-Version: 2.3
Name: python-dmon
Version: 0.3.0
Summary: A lightweight, cross-platform daemon manager that runs any command as a background process.
Keywords: python-dmon,dmon,daemon,background,detach,process management
Author: Atomie CHEN
Author-email: Atomie CHEN <atomic_cwh@163.com>
Requires-Dist: colorama>=0.4.6
Requires-Dist: psutil>=7.1.0
Requires-Dist: pyyaml>=6.0.3
Requires-Dist: termcolor>=2.4.0
Requires-Dist: tomli>=2.2.1 ; python_full_version < '3.11'
Requires-Python: >=3.8
Project-URL: Bug Tracker, https://github.com/atomiechen/python-dmon/issues
Project-URL: Changelog, https://github.com/atomiechen/python-dmon/blob/main/CHANGELOG.md
Project-URL: Homepage, https://github.com/atomiechen/python-dmon
